StatsVars/StatsVars.py
StatsVars/__init__.py
StatsVars-0.0.3.dist-info/LICENSE
StatsVars-0.0.3.dist-info/METADATA
StatsVars-0.0.3.dist-info/WHEEL
StatsVars-0.0.3.dist-info/top_level.txt
StatsVars-0.0.3.dist-info/RECORD
