Metadata-Version: 2.1
Name: StatsVars
Version: 0.0.3
Summary: Library of Statistical Calculations
Home-page: https://github.com/dchequer/stats_vars
Author: Diego Chequer
Author-email: millychequer@gmail.com
Project-URL: Bug Tracker, https://github.com/dchequer/stats_vars/issues
Classifier: Programming Language :: Python :: 3
Classifier: License :: OSI Approved :: MIT License
Classifier: Operating System :: OS Independent
Requires-Python: >=3.6
License-File: LICENSE
